odoo10_addon_contract_membership_delegated_partner-10.0.1.0.0-py2.7-nspkg.pth
odoo/addons/contract_membership_delegated_partner/README.rst
odoo/addons/contract_membership_delegated_partner/__init__.py
odoo/addons/contract_membership_delegated_partner/__manifest__.py
odoo/addons/contract_membership_delegated_partner/i18n/es.po
odoo/addons/contract_membership_delegated_partner/models/__init__.py
odoo/addons/contract_membership_delegated_partner/models/account_analytic_account.py
odoo/addons/contract_membership_delegated_partner/tests/__init__.py
odoo/addons/contract_membership_delegated_partner/tests/test_delegated_partner_contract.py
odoo/addons/contract_membership_delegated_partner/views/account_analytic_account_view.xml
odoo10_addon_contract_membership_delegated_partner-10.0.1.0.0.dist-info/DESCRIPTION.rst
odoo10_addon_contract_membership_delegated_partner-10.0.1.0.0.dist-info/METADATA
odoo10_addon_contract_membership_delegated_partner-10.0.1.0.0.dist-info/RECORD
odoo10_addon_contract_membership_delegated_partner-10.0.1.0.0.dist-info/WHEEL
odoo10_addon_contract_membership_delegated_partner-10.0.1.0.0.dist-info/metadata.json
odoo10_addon_contract_membership_delegated_partner-10.0.1.0.0.dist-info/namespace_packages.txt
odoo10_addon_contract_membership_delegated_partner-10.0.1.0.0.dist-info/top_level.txt
